triplepy/__init__.py
triplepy/numerical_evaluation.py
triplepy/postprocessing.py
triplepy/set_input_parameters.py
triplepy/sharp_interface_solution.py
triplepy/vtk_io.py
triplepy-1.0.0.dist-info/METADATA
triplepy-1.0.0.dist-info/WHEEL
triplepy-1.0.0.dist-info/licenses/LICENSE
triplepy-1.0.0.dist-info/RECORD
