Metadata-Version: 2.3
Name: triplepy
Version: 1.0.0
Summary: A benchmark for GB migration subject to capillary and bulk driving forces.
Project-URL: Homepage, https://github.com/Triple-Junction/triplepy
Project-URL: Issues, https://github.com/Triple-Junction/triplepy/issues
Author-email: Paul Hoffrogge <mail@paul-hoffrogge.de>, Simon Daubner <simon.daubner@kit.edu>, Bei Zhou <b.zhou@access-technology.de>
Classifier: License :: OSI Approved :: MIT License
Classifier: Operating System :: OS Independent
Classifier: Programming Language :: Python :: 3
Requires-Python: >=3.8
Requires-Dist: mip
Requires-Dist: numpy
Requires-Dist: pint
Requires-Dist: scikit-image
Requires-Dist: scipy
Requires-Dist: vtk
Provides-Extra: test
Requires-Dist: pytest; extra == 'test'
